Metadata-Version: 2.1
Name: polywrapper
Version: 0.1.5
Summary: A wrapper for interacting with Polygon DB
Author: David
Author-email: dwatnip123@gmail.com
License-File: LICENSE
Requires-Dist: websocket-client
